pymcs/__init__.py
pymcs/cli.py
pymcs/converters.py
pymcs/db_tools.py
pymcs/io.py
pymcs-0.4.5.dist-info/LICENSE
pymcs-0.4.5.dist-info/WHEEL
pymcs-0.4.5.dist-info/METADATA
pymcs-0.4.5.dist-info/RECORD
