Metadata-Version: 2.1
Name: pymcs
Version: 0.4.5
Summary: Top-level package for pymcs.
Home-page: https://github.com/michaelaye/pymcs
License: BSD-3-Clause
Keywords: mars,planetary,atmosphere
Author: K.-Michael Aye
Author-email: kmichael.aye@gmail.com
Requires-Python: ~=3.7
Classifier: Development Status :: 4 - Beta
Classifier: Intended Audience :: Developers
Classifier: Intended Audience :: Science/Research
Classifier: License :: OSI Approved :: BSD License
Classifier: Natural Language :: English
Classifier: Programming Language :: Python :: 3
Classifier: Programming Language :: Python :: 3.7
Classifier: Programming Language :: Python :: 3.8
Requires-Dist: pandas >=0.25
Requires-Dist: tqdm >=4.41
Requires-Dist: cx_Oracle >= 7.3
